hostparse/__init__.py
hostparse/__main__.py
hostparse/hostparse.py
hostparse-0.0.2.dist-info/LICENSE
hostparse-0.0.2.dist-info/METADATA
hostparse-0.0.2.dist-info/WHEEL
hostparse-0.0.2.dist-info/entry_points.txt
hostparse-0.0.2.dist-info/top_level.txt
hostparse-0.0.2.dist-info/RECORD
