Metadata-Version: 2.1
Name: hostparse
Version: 0.0.2
Summary: A command-line client for URL and hostname swizzling 
Home-page: https://github.com/0x3a/hostparse
Author: Yonathan Klijnsma
Author-email: admin@0x3a.com
License: UNKNOWN
Platform: UNKNOWN
Classifier: Programming Language :: Python :: 3
Classifier: License :: OSI Approved :: MIT License
Classifier: Operating System :: OS Independent
Requires-Dist: tldextract
